Workbook

Sheet - AYUDA -
B4: Ayuda

Sheet Precios nosotros
B5: Comparación de Precios entre diferentes proveedores
B6: Ingresa en la tabla los productos, los proveedores y sus precios
J7: ESTADÍSTICAS POR PRODUCTO
B8: PRODUCTO | C8: CANTIDAD | D8: PROVEEDOR 1 | E8: PROVEEDOR 2 | F8: PROVEEDOR 3 | G8: PROVEEDOR 4 | H8: PROVEEDOR 5 | I8: PROVEEDOR 6 | J8: PRECIO MÁS BAJO | K8: PRECIO PROMEDIO | L8: PRECIO MÁS ALTO
B9: Torre PC | C9: 3 | D9: ='[1]Torres '!$H$8 -> 2204910 | E9: ='[1]Torres '!$H$9 -> 2294915 | F9: ='[1]Torres '!$G$10 -> 8820000 | J9: =MIN('Precios nosotros'!$D9:$I9) -> 2204910 | K9: =IFERROR(AVERAGE('Precios nosotros'!$D9:$I9),0) -> 4439941.7 | L9: =MAX('Precios nosotros'!$D9:$I9) -> 8820000
B10: Monitor | C10: 3 | D10: =[1]monitor!$H$8 -> 749900 | E10: =[1]monitor!$H$9 -> 749900 | F10: =[1]monitor!$H$10 -> 861900 | J10: =MIN('Precios nosotros'!$D10:$I10) -> 749900 | K10: =IFERROR(AVERAGE('Precios nosotros'!$D10:$I10),0) -> 787233.33 | L10: =MAX('Precios nosotros'!$D10:$I10) -> 861900
B11: Portatil | C11: 3 | D11: ='[1]computador portatil'!$H$8 -> 3558870 | E11: ='[1]computador portatil'!$H$9 -> 3999900 | F11: ='[1]computador portatil'!$H$10 -> 3599000 | J11: =MIN('Precios nosotros'!$D11:$I11) -> 3558870 | K11: =IFERROR(AVERAGE('Precios nosotros'!$D11:$I11),0) -> 3719256.7 | L11: =MAX('Precios nosotros'!$D11:$I11) -> 3999900
B12: Hosting | C12: 1 | D12: ='[1]+hosting'!$H$8 -> 300000 | E12: ='[1]+hosting'!$H$9 -> 469743.79 | F12: ='[1]+hosting'!$H$10 -> 371700 | J12: =MIN('Precios nosotros'!$D12:$I12) -> 300000 | K12: =IFERROR(AVERAGE('Precios nosotros'!$D12:$I12),0) -> 380481.26 | L12: =MAX('Precios nosotros'!$D12:$I12) -> 469743.79
B13: Teclado | C13: 3 | D13: =[1]teclados!$H$8 -> 79900 | E13: =[1]teclados!$H$9 -> 28900 | F13: =[1]teclados!$H$10 -> 54900 | J13: =MIN('Precios nosotros'!$D13:$I13) -> 28900 | K13: =IFERROR(AVERAGE('Precios nosotros'!$D13:$I13),0) -> 54566.667 | L13: =MAX('Precios nosotros'!$D13:$I13) -> 79900
B14: Mouses | C14: 3 | D14: =[1]Moueses!$H$8 -> 23100 | E14: =[1]Moueses!$H$9 -> 20000 | F14: =[1]Moueses!$H$10 -> 54900 | J14: =MIN('Precios nosotros'!$D14:$I14) -> 20000 | K14: =IFERROR(AVERAGE('Precios nosotros'!$D14:$I14),0) -> 32666.667 | L14: =MAX('Precios nosotros'!$D14:$I14) -> 54900
B15: Antivirus | C15: 3 | D15: =[1]Antivirus!$H$8 -> 159990 | E15: =[1]Antivirus!$H$9 -> 160000 | F15: =[1]Antivirus!$H$10 -> 432000 | J15: =MIN('Precios nosotros'!$D15:$I15) -> 159990 | K15: =IFERROR(AVERAGE('Precios nosotros'!$D15:$I15),0) -> 250663.33 | L15: =MAX('Precios nosotros'!$D15:$I15) -> 432000
B16: Mockup | C16: 6 | D16: =[1]mockup!$H$8 -> 191668.4 | E16: =[1]mockup!$H$9 -> 15607.284 | F16: =[1]mockup!$H$10 -> 64541.4 | J16: =MIN('Precios nosotros'!$D16:$I16) -> 15607.284 | K16: =IFERROR(AVERAGE('Precios nosotros'!$D16:$I16),0) -> 90605.695 | L16: =MAX('Precios nosotros'!$D16:$I16) -> 191668.4
B17: Internet | C17: 1 | D17: =[1]internet!$H$8 -> 76792 | E17: =[1]internet!$H$9 -> 52950 | F17: =[1]internet!$H$10 -> 442600 | J17: =MIN('Precios nosotros'!$D17:$I17) -> 52950 | K17: =IFERROR(AVERAGE('Precios nosotros'!$D17:$I17),0) -> 190780.67 | L17: =MAX('Precios nosotros'!$D17:$I17) -> 442600
B18: Editores de codigo | C18: 3 | D18: ='[1]editores de codigo'!$H$8 -> 388401.75 | E18: ='[1]editores de codigo'!$H$9 -> 231471.75 | F18: ='[1]editores de codigo'!$H$10 -> 176546.25 | J18: =MIN('Precios nosotros'!$D18:$I18) -> 176546.25 | K18: =IFERROR(AVERAGE('Precios nosotros'!$D18:$I18),0) -> 265473.25 | L18: =MAX('Precios nosotros'!$D18:$I18) -> 388401.75
B19: Bases de datos | C19: 1 | D19: ='[1]bases de datos'!$H$8 -> 222961.2 | E19: ='[1]bases de datos'!$H$9 -> 1961875 | F19: ='[1]bases de datos'!$H$10 -> 273.9 | J19: =MIN('Precios nosotros'!$D19:$I19) -> 273.9 | K19: =IFERROR(AVERAGE('Precios nosotros'!$D19:$I19),0) -> 728370.03 | L19: =MAX('Precios nosotros'!$D19:$I19) -> 1961875
B20: Dominio | C20: 1 | D20: =[1]dominio!$H$8 -> 16900 | E20: =[1]dominio!$H$9 -> 52500 | F20: =[1]dominio!$H$10 -> 51251 | J20: =MIN('Precios nosotros'!$D20:$I20) -> 16900 | K20: =IFERROR(AVERAGE('Precios nosotros'!$D20:$I20),0) -> 40217 | L20: =MAX('Precios nosotros'!$D20:$I20) -> 52500
B21: Microsoft | C21: 1 | D21: ='[1]suscripciones o servicios'!$H$8 -> 349999 | E21: ='[1]suscripciones o servicios'!$H$9 -> 219000 | F21: ='[1]suscripciones o servicios'!$H$10 -> 289900 | J21: =MIN('Precios nosotros'!$D21:$I21) -> 219000 | K21: =IFERROR(AVERAGE('Precios nosotros'!$D21:$I21),0) -> 286299.67 | L21: =MAX('Precios nosotros'!$D21:$I21) -> 349999
J22: =MIN('Precios nosotros'!$D22:$I22) -> 0 | K22: =IFERROR(AVERAGE('Precios nosotros'!$D22:$I22),0) -> 0 | L22: =MAX('Precios nosotros'!$D22:$I22) -> 0
J23: =MIN('Precios nosotros'!$D23:$I23) -> 0 | K23: =IFERROR(AVERAGE('Precios nosotros'!$D23:$I23),0) -> 0 | L23: =MAX('Precios nosotros'!$D23:$I23) -> 0
J24: =MIN('Precios nosotros'!$D24:$I24) -> 0 | K24: =IFERROR(AVERAGE('Precios nosotros'!$D24:$I24),0) -> 0 | L24: =MAX('Precios nosotros'!$D24:$I24) -> 0
B25: Total | D25: =ROUND(SUMPRODUCT(C9:C24,D9:D24),2) -> 23611878 | E25: =ROUND(SUMPRODUCT(C9:C24,E9:E24),2) -> 25304973 | F25: =ROUND(SUMPRODUCT(C9:C24,F9:F24),2) -> 43540712 | G25: =ROUND(SUMPRODUCT(C9:C24,G9:G24),2) -> 0 | H25: =ROUND(SUMPRODUCT(C9:C24,H9:H24),2) -> 0 | I25: =ROUND(SUMPRODUCT(C9:C24,I9:I24),2) -> 0
B28: DATOS ADICIONALES
B29: TIEMPO DE ENTREGA (DÍAS) | D29: 12 | E29: 1 | F29: 0
B30: COSTO DE ENVÍO | D30: 12727 | E30: 10000 | F30: 9000
B31: FORMAS DE PAGO | D31: codensa | E31: Visa | F31: efecty | G31: PSE
D32: american express | E32: Master card | F32: Bancolombia | G32: nequi

Sheet Preios admin
B5: Comparación de Precios entre diferentes proveedores
B6: Ingresa en la tabla los productos, los proveedores y sus precios
J7: ESTADÍSTICAS POR PRODUCTO
B8: PRODUCTO | C8: CANTIDAD | D8: PROVEEDOR 1 | E8: PROVEEDOR 2 | F8: PROVEEDOR 3 | G8: PROVEEDOR 4 | H8: PROVEEDOR 5 | I8: PROVEEDOR 6 | J8: PRECIO MÁS BAJO | K8: PRECIO PROMEDIO | L8: PRECIO MÁS ALTO
B9: Torre PC | C9: 1 | D9: ='[1]Torres '!$H$8 -> 2204910 | E9: ='[1]Torres '!$H$9 -> 2294915 | F9: ='[1]Torres '!$G$10 -> 8820000 | J9: =MIN('Preios admin'!$D9:$I9) -> 2204910 | K9: =IFERROR(AVERAGE('Preios admin'!$D9:$I9),0) -> 4439941.7 | L9: =MAX('Preios admin'!$D9:$I9) -> 8820000
B10: Monitor | C10: 1 | D10: =[1]monitor!$H$8 -> 749900 | E10: =[1]monitor!$H$9 -> 749900 | F10: =[1]monitor!$H$10 -> 861900 | J10: =MIN('Preios admin'!$D10:$I10) -> 749900 | K10: =IFERROR(AVERAGE('Preios admin'!$D10:$I10),0) -> 787233.33 | L10: =MAX('Preios admin'!$D10:$I10) -> 861900
B11: Portatil | C11: 1 | D11: ='[1]computador portatil'!$H$8 -> 3558870 | E11: ='[1]computador portatil'!$H$9 -> 3999900 | F11: ='[1]computador portatil'!$H$10 -> 3599000 | J11: =MIN('Preios admin'!$D11:$I11) -> 3558870 | K11: =IFERROR(AVERAGE('Preios admin'!$D11:$I11),0) -> 3719256.7 | L11: =MAX('Preios admin'!$D11:$I11) -> 3999900
B12: Hosting | C12: 1 | D12: ='[1]+hosting'!$H$8 -> 300000 | E12: ='[1]+hosting'!$H$9 -> 469743.79 | F12: ='[1]+hosting'!$H$10 -> 371700 | J12: =MIN('Preios admin'!$D12:$I12) -> 300000 | K12: =IFERROR(AVERAGE('Preios admin'!$D12:$I12),0) -> 380481.26 | L12: =MAX('Preios admin'!$D12:$I12) -> 469743.79
B13: Teclado | C13: 1 | D13: =[1]teclados!$H$8 -> 79900 | E13: =[1]teclados!$H$9 -> 28900 | F13: =[1]teclados!$H$10 -> 54900 | J13: =MIN('Preios admin'!$D13:$I13) -> 28900 | K13: =IFERROR(AVERAGE('Preios admin'!$D13:$I13),0) -> 54566.667 | L13: =MAX('Preios admin'!$D13:$I13) -> 79900
B14: Mouses | C14: 1 | D14: =[1]Moueses!$H$8 -> 23100 | E14: =[1]Moueses!$H$9 -> 20000 | F14: =[1]Moueses!$H$10 -> 54900 | J14: =MIN('Preios admin'!$D14:$I14) -> 20000 | K14: =IFERROR(AVERAGE('Preios admin'!$D14:$I14),0) -> 32666.667 | L14: =MAX('Preios admin'!$D14:$I14) -> 54900
B15: Antivirus | C15: 1 | D15: =[1]Antivirus!$H$8 -> 159990 | E15: =[1]Antivirus!$H$9 -> 160000 | F15: =[1]Antivirus!$H$10 -> 432000 | J15: =MIN('Preios admin'!$D15:$I15) -> 159990 | K15: =IFERROR(AVERAGE('Preios admin'!$D15:$I15),0) -> 250663.33 | L15: =MAX('Preios admin'!$D15:$I15) -> 432000
B16: Mockup | C16: 1 | D16: =[1]mockup!$H$8 -> 191668.4 | E16: =[1]mockup!$H$9 -> 15607.284 | F16: =[1]mockup!$H$10 -> 64541.4 | J16: =MIN('Preios admin'!$D16:$I16) -> 15607.284 | K16: =IFERROR(AVERAGE('Preios admin'!$D16:$I16),0) -> 90605.695 | L16: =MAX('Preios admin'!$D16:$I16) -> 191668.4
B17: Internet | C17: 1 | D17: =[1]internet!$H$8 -> 76792 | E17: =[1]internet!$H$9 -> 52950 | F17: =[1]internet!$H$10 -> 442600 | J17: =MIN('Preios admin'!$D17:$I17) -> 52950 | K17: =IFERROR(AVERAGE('Preios admin'!$D17:$I17),0) -> 190780.67 | L17: =MAX('Preios admin'!$D17:$I17) -> 442600
B18: Editores de codigo | C18: 1 | D18: ='[1]editores de codigo'!$H$8 -> 388401.75 | E18: ='[1]editores de codigo'!$H$9 -> 231471.75 | F18: ='[1]editores de codigo'!$H$10 -> 176546.25 | J18: =MIN('Preios admin'!$D18:$I18) -> 176546.25 | K18: =IFERROR(AVERAGE('Preios admin'!$D18:$I18),0) -> 265473.25 | L18: =MAX('Preios admin'!$D18:$I18) -> 388401.75
B19: Bases de datos | C19: 1 | D19: ='[1]bases de datos'!$H$8 -> 222961.2 | E19: ='[1]bases de datos'!$H$9 -> 1961875 | F19: ='[1]bases de datos'!$H$10 -> 273.9 | J19: =MIN('Preios admin'!$D19:$I19) -> 273.9 | K19: =IFERROR(AVERAGE('Preios admin'!$D19:$I19),0) -> 728370.03 | L19: =MAX('Preios admin'!$D19:$I19) -> 1961875
B20: Dominio | C20: 1 | D20: =[1]dominio!$H$8 -> 16900 | E20: =[1]dominio!$H$9 -> 52500 | F20: =[1]dominio!$H$10 -> 51251 | J20: =MIN('Preios admin'!$D20:$I20) -> 16900 | K20: =IFERROR(AVERAGE('Preios admin'!$D20:$I20),0) -> 40217 | L20: =MAX('Preios admin'!$D20:$I20) -> 52500
B21: Microsoft | C21: 1 | D21: ='[1]suscripciones o servicios'!$H$8 -> 349999 | E21: ='[1]suscripciones o servicios'!$H$9 -> 219000 | F21: ='[1]suscripciones o servicios'!$H$10 -> 289900 | J21: =MIN('Preios admin'!$D21:$I21) -> 219000 | K21: =IFERROR(AVERAGE('Preios admin'!$D21:$I21),0) -> 286299.67 | L21: =MAX('Preios admin'!$D21:$I21) -> 349999
J22: =MIN('Preios admin'!$D22:$I22) -> 0 | K22: =IFERROR(AVERAGE('Preios admin'!$D22:$I22),0) -> 0 | L22: =MAX('Preios admin'!$D22:$I22) -> 0
J23: =MIN('Preios admin'!$D23:$I23) -> 0 | K23: =IFERROR(AVERAGE('Preios admin'!$D23:$I23),0) -> 0 | L23: =MAX('Preios admin'!$D23:$I23) -> 0
J24: =MIN('Preios admin'!$D24:$I24) -> 0 | K24: =IFERROR(AVERAGE('Preios admin'!$D24:$I24),0) -> 0 | L24: =MAX('Preios admin'!$D24:$I24) -> 0
B25: Total | D25: =ROUND(SUMPRODUCT(C9:C24,D9:D24),2) -> 8323392.3 | E25: =ROUND(SUMPRODUCT(C9:C24,E9:E24),2) -> 10256763 | F25: =ROUND(SUMPRODUCT(C9:C24,F9:F24),2) -> 15219513 | G25: =ROUND(SUMPRODUCT(C9:C24,G9:G24),2) -> 0 | H25: =ROUND(SUMPRODUCT(C9:C24,H9:H24),2) -> 0 | I25: =ROUND(SUMPRODUCT(C9:C24,I9:I24),2) -> 0
B28: DATOS ADICIONALES
B29: TIEMPO DE ENTREGA (DÍAS) | D29: 12 | E29: 1 | F29: 0
B30: COSTO DE ENVÍO | D30: 12727 | E30: 10000 | F30: 9000
B31: FORMAS DE PAGO | D31: codensa | E31: Visa | F31: efecty | G31: PSE
D32: american express | E32: Master card | F32: Bancolombia | G32: nequi

Sheet Soporte
B7: Almendras | C7: 1 | D7: 498 | E7: 420 | F7: 450 | G7: 230 | H7: 600 | I7: 520
B8: Nueces | C8: 2 | D8: 450 | E8: 220 | F8: 405 | G8: 495 | H8: 540 | I8: 200
B9: Pistachos | C9: 2 | D9: 650 | E9: 620 | F9: 666 | G9: 400 | H9: 648 | I9: 452.4
B10: Pecán | C10: 1 | D10: 585 | E10: 558 | F10: 320 | G10: 360 | H10: 583.2 | I10: 407.16
B11: Bananas | C11: 3 | D11: 526.5 | E11: 502.2 | F11: 539.46 | G11: 300 | H11: 500 | I11: 366.44
B12: Pasas | C12: 1 | D12: 473.8 | E12: 200 | F12: 485.51 | G12: 291.6 | H12: 270 | I12: 220
D19: 30 | E19: 10 | F19: 15 | G19: 15 | H19: 15 | I19: 10
D20: 10 | E20: 10 | F20: 10 | G20: Gratis | H20: 5 | I20: Gratis
D21: Efvo | E21: Efvo | F21: Mercado Pago | G21: Efectivo | H21: Mercado Pago | I21: Mercado Pago
D22: Tarjeta | E22: Tarjeta | F22: Tarjeta cuotas | G22: Mercado Pago | H22: Tarjeta cuotas | I22: Tarjeta cuotas
B28: Piñones | C28: 1 | D28: 340 | E28: 330 | F28: 440 | G28: 400 | H28: 320 | I28: 330
B29: Cranberries | C29: 1 | D29: 220 | E29: 230 | F29: 240 | G29: 220 | H29: 219 | I29: 218
B30: Castañas | C30: 2 | D30: 560 | E30: 580 | F30: 550 | G30: 520 | H30: 551 | I30: 550
B35: China Co
B36: 250
B37: 440
B38: 440
B39: 350
B40: 420
B41: 199
